earth_cam_downloader/__init__.py
earth_cam_downloader/m3u8_downloader.py
earth_cam_downloader-0.0.1.dist-info/METADATA
earth_cam_downloader-0.0.1.dist-info/WHEEL
earth_cam_downloader-0.0.1.dist-info/top_level.txt
earth_cam_downloader-0.0.1.dist-info/RECORD
